nonebot_plugin_alipayvoice/__init__.py
nonebot_plugin_alipayvoice-0.5.0.dist-info/WHEEL
nonebot_plugin_alipayvoice-0.5.0.dist-info/METADATA
nonebot_plugin_alipayvoice-0.5.0.dist-info/license_files/LICENSE
nonebot_plugin_alipayvoice-0.5.0.dist-info/RECORD
